qcextender/__init__.py
qcextender/basewaveform.py
qcextender/dimensionlesswaveform.py
qcextender/functions.py
qcextender/generators/__init__.py
qcextender/generators/backends/__init__.py
qcextender/generators/backends/lal_backend.py
qcextender/generators/backends/phenomx_backend.py
qcextender/generators/registry.py
qcextender/metadata.py
qcextender/units.py
qcextender/waveform.py
qcextender-0.4.7.dist-info/WHEEL
qcextender-0.4.7.dist-info/METADATA
qcextender-0.4.7.dist-info/RECORD
