Metadata-Version: 2.3
Name: qcextender
Version: 0.4.7
Summary: This package aims to extend any quasi-circular waveform with complex features.
Author-email: aminrouanserik@gmail.com
Requires-Dist: gwpy>=3.0.13
Requires-Dist: lalsuite>=7.26.1
Requires-Dist: pycbc>=2.9.0
Requires-Dist: sxs>=2025.0.12
Requires-Python: >=3.12
